{
    "timezone": {
        "europe_istanbul": "{{value}} Istambuł",
        "europe_moscow": "{{value}} Moskwa, St. Petersburg, Wołgograd (RTZ 2)",
        "europe_warsaw": "{{value}} Sarajewo, Skopje, Warszawa, Zagrzeb",
        "pacific_bougainville": "{{value}} Standardowy Czas Bouganville",
        "africa_harare": "{{value}} Harare, Pretoria",
        "africa_nairobi": "{{value}} Nairobi",
        "america_adak": "{{value}} Adak",
        "america_asuncion": "{{value}} Asuncion",
        "america_caracas": "{{value}} Caracas",
        "america_cuiaba": "{{value}} Cuiaba",
        "america_guatemala": "{{value}} Ameryka Środkowa",
        "america_indiana_indianapolis": "{{value}} Indiana (Wschód)",
        "america_montevideo": "{{value}} Montevideo",
        "america_punta_arenas": "{{value}} Punta Arenas",
        "america_st_johns": "{{value}} Nowa Fundlandia",
        "asia_amman": "{{value}} Jordania",
        "asia_barnaul": "{{value}} Barnaul",
        "asia_damascus": "{{value}} Damaszek",
        "asia_hovd": "{{value}} Kobdo",
        "asia_kamchatka": "{{value}} Anadyr, Pietropawłowsk Kamczacki (RTZ 11)",
        "asia_krasnoyarsk": "{{value}} Krasnojarsk (RTZ 6)",
        "asia_muscat": "{{value}} Abu Dabi, Maskat",
        "asia_qyzylorda": "{{value}} Kyzyłorda",
        "asia_srednekolymsk": "{{value}} Czokurdach (RTZ 10)",
        "asia_tehran": "{{value}} Teheran",
        "asia_vladivostok": "{{value}} Władywostok, Magadan (RTZ 9)",
        "asia_yerevan": "{{value}} Erywań",
        "australia_adelaide": "{{value}} Adelaide",
        "australia_hobart": "{{value}} Hobart",
        "etc_gmt+12": "{{value}} Linia zmiany daty",
        "europe_berlin": "{{value}} Amsterdam, Berlin, Berno, Rzym, Sztokholm, Wiedeń",
        "pacific_fiji": "{{value}} Fidżi",
        "pacific_kiritimati": "{{value}} Kiritimati",
        "pacific_tongatapu": "{{value}} Nuku'alofa"
    },
    "buckets": {
        "connection": {
            "verify_connector": "ZWERYFIKUJ ŁĄCZNIK",
            "arn_name": "Arn / Nazwa"
        },
        "connect_buckets": "Połącz buckety",
        "summary": {
            "access_key": "Klucz dostępu",
            "secret_key": "Tajny klucz"
        },
        "alibaba_regions": {
            "ap_northeast_1": "Japonia (Tokyo)",
            "ap_southeast_3": "Malezja (Kuala Lumpur)",
            "cn_hangzhou": "Chiny (Hangzhou)",
            "cn_shenzhen": "Chiny (Shenzen)",
            "me_east_1": "ZEA Dubaj"
        },
        "amazon_regions": {
            "ap_northeast_1": "Azja Pacyfik (Tokyo)",
            "ap_southeast_2": "Azja Pacyfik (Sydney)",
            "eu_north_1": "UE (Sztokholm)",
            "govcloud": "AWS GovCloud (USA)",
            "us_east_1": "USA Wschód (Północna Wirginia)",
            "af_south_1": "Afryka (Cape Town)"
        },
        "invalid_compression_thresold": "Wymagany jest próg kompresji",
        "s3_types": {
            "amazone_web_service_s3": "Amazon Web Service S3",
            "emc_s3": "EMC S3",
            "minio": "Minio"
        }
    },
    "core": {
        "subscription": {
            "company_name": "Nazwa firmy",
            "features": "Rozwiń",
            "subscription_last_check": "Ostatnie sprawdzenie subskrypcji",
            "modal": {
                "warning": "Próbujesz deaktywować aktualny token. Jego deaktywacja wyłączy wszystkie włączone funkcje.",
                "cancel": "NIE"
            },
            "order_id": "ID zamówienia"
        }
    },
    "domain": {
        "free_busy": "Wolny/zajęty",
        "authentication": "Uwierzytelnianie",
        "most_result_return_gal_search": "Najwięcej wyników zwróconych przez wyszukiwanie GLA",
        "many_domain_info_msg": "Ale dużo domen! Którą z nich chcesz zobaczyć? Aby filtrować, zacznij wpisywać.",
        "send_the_warning_to": "Wyślij ostrzeżenie do",
        "mail_server": "Serwer poczty",
        "account_list": "Lista kont",
        "max_result_return_gal_search": "Max. liczba wyników pokazywanych przy wyszukiwaniu GLA",
        "certificate_type_use_custom": "Chcę użyć niestandardowego certyfikatu",
        "certificate_saved": "Certyfikaty zostały zapisane",
        "private_key_certificate_removed": "Prywatny klucz certyfikatu został usunięty",
        "unit_measure_hours": "Godziny",
        "ldap": "LDAP"
    },
    "label": {
        "accounts": "Konta",
        "backup": "Kopia zapasowa",
        "delete": "Usuń",
        "hours": "Godziny",
        "not_set": "Nie ustawiono",
        "page ": "Zaakceptowano prośbę o udostępnienie",
        "save": "Zapisz",
        "suspended": "Zawieszone",
        "active": "Aktywne",
        "closed": "Wyłączone",
        "external_active_directory": "Zewnętrzny katalog aktywny",
        "general_information": "Informacje ogólne",
        "maintenance": "W trakcie prac",
        "automatically_add_invites_with_PUBLISH_method": "Automatycznie dodawaj zaproszenia metodą PUBLISH",
        "access_key": "Klucz dostępu",
        "advanced": "Zaawansowane",
        "always_show_the_mini-calendar": "Zawsze pokazuj minikalendarz",
        "draft_auto_save_interval": "Interwał automatycznego zapisu kopii roboczej",
        "enable_past_due_reminders": "Włącz przypomnienia o spotkaniach z przeszłości",
        "general_settings": "Ustawienia ogólne",
        "initial_calendar_view": "Wstępny widok kalendarza",
        "members": "Członkowie",
        "new_domain": "Nowa domena",
        "pending": "Oczekujące",
        "resources": "Zasoby",
        "search": "Wyszukaj",
        "show_time_zone_list_in_appointment_view": "Pokaż listę stref czasowych w widoku spotkań",
        "type": "Typ",
        "use_iCal_delegation_model_for_shared_calendars_for_CalDAV_interface": "Używaj modelu delegacji iCal dla udostępnionych kalendarzy w interfejsie CalDAV",
        "auto": "Automatycznie",
        "bucket_done_button": "Gotowe",
        "account_status": "Status konta",
        "go_back": "Powrót",
        "mail": "Skrzynka pocztowa",
        "require_list_owner_approval": "Wymagaj zatwierdzenia przez właściciela listy",
        "standard": "Standardowe",
        "yes": "Tak",
        "virtual_host_info_msg": "Wirtualne hosty pozwalają systemowi utworzyć domyślną domenę logowania dla użytkownika.",
        "auto_accept_auto_decline_on_conflict": "Automatyczna akceptacja jeżeli to możliwe, automatyczne odrzucenie w przypadku konfliktu",
        "you_are_deleting": "Usuwasz {{cosname}}",
        "virtual_host_user_msg": "Każdy użytkownik, który zaloguje się przy użyciu URL z jedną z poniższych nazw hostów, będzie znajdował się w domenie {{domainName}}",
        "viewed_name": "Wyświetlana nazwa (automatyczne uzupełnianie)",
        "verify_connector_fail": "WERYFIKACJA SIĘ NIE POWIODŁA",
        "utility_view2": "Testuj widok praktyczny 2",
        "userName": "użytkownik (automatycznie uzupełniony)",
        "this_list_is_empty": "Ta lista jest pusta.",
        "subscriptions": "Subskrypcje",
        "show_reminder": "Pokaż przypomnienie",
        "server_pools": "Pule serwerów",
        "seconds": "Sekundy",
        "secondary?bar_view": "To jest główny widok",
        "search_an_account": "Wyszukaj konto",
        "restore_deleted_email": "Przywróć usunięty e-mail",
        "public_service_protocol": "Protokół dla public service",
        "password_lenght_msg": "Hasło musi być dłuższe niż 5 znaków",
        "no_go_back": "Nie, powróć",
        "never_logged_in": "Nigdy nie zalogowano",
        "mx_record_information_msg": "Jeżeli Twoje MX records kierują się do spam-relay lub innego zewnętrznego serwera, wpisz nazwę tego serwera w pole \"Nazwa przychodzącego hosta SMTP\".",
        "manual_accept_auto_decline_on_conflict": "Ręczna akceptacja, automatyczne odrzucenie w przypadku konfliktu",
        "mailing_lists": "Listy dystrybucyjne",
        "mailing_list": "Lista dystrybucyjna",
        "list_url": "URL listy dystrybucyjnej",
        "inbound_smtp_host_name": "Nazwa przychodzącego hosta SMTP",
        "https": "https",
        "gay_sync_account_name": "Nazwa konta GLA Sync",
        "first_day_of_Week": "Pierwszy dzień tygodnia",
        "enter_email_address": "Wpisz adres e-mail",
        "domain_quota_settings": "Ustawienia limitu przestrzeni dla domeny",
        "deleting_cos_msg": "Usuwanie <bold>{{cosname}}</bold>",
        "delete_domain": "Usuń domenę",
        "delete_bucket_sucess": "{{name}} zostało usunięte",
        "default_font_size": "Domyślny rozmiar czcionki",
        "datasource_name_for_internal_gal": "Nazwa datasource dla wewnętrzego GLA",
        "create_new_cos": "Stwórz nowe COS",
        "create_cos_success_msg": "{{cosName}} zostało stworzone pomyślnie",
        "console_redirection": "Przekierowanie konsoli",
        "connect_buckets": "Połącz buckety",
        "cancle_button": "NIE",
        "buckets": "Buckety",
        "block_send_receive": "Blokuj wysyłanie/odbieranie",
        "add_to_the_list": "Dodaj do listy",
        "account_created_successfully": "Konto zostało stworzone pomyślnie",
        "auto_negation": "Automatycznie odrzucaj",
        "always_compose_mail_using": "Zawsze twórz e-maile używając",
        "admins": "Administratorzy",
        "calendar": "Kalendarz",
        "compression": "Kompresja",
        "current": "Aktualne",
        "destination_account": "Konto docelowe",
        "edit_button": "EDYTUJ",
        "helo": "Pomoc",
        "mailing_options": "Ustawienia e-maili",
        "new_volume_create": "STWÓRZ",
        "private": "Prywatne",
        "restore_data_source": "Przywróć źródło danych",
        "volume": "Wolumin",
        "volume_compression_thresold": "Limit kompresji",
        "volume_next_step_button": "NASTĘPNY KROK",
        "week_day": {
            "monday": "Poniedziałek",
            "tuesday": "Wtorek"
        },
        "who_needs_receive_this_email": "Kto otrzyma powiadomienie?",
        "volume_main": "Główny wolumin",
        "username_with": "nazwa użytkownika z",
        "start": "start",
        "share_message_to_new_member": "Udostępnij wiadomość nowym użytkownikom",
        "select_an_account": "Wybierz konto",
        "receiving_mails": "Otrzymywanie e-maili",
        "operations": "Operacje",
        "new_volume_button": "NOWY WOLUMIN",
        "min_threshold": "Min. próg",
        "max_quota_allowed": "Max. dozwolony limit przestrzeni",
        "main": "Główne",
        "local_ldap": "Lokalne LDAP",
        "i_want_to_send_invites_to_resource": "Przekazuj dalej zaproszenia w kalendarzu na te adresy",
        "group_by": "Grupuj wg",
        "example": "przykład",
        "email_notification": "Powiadomienia e-mail",
        "default_charset": "Domyślny zestaw znaków",
        "create_resource_success_msg": "{{resourceName}} zostało pomyślnie stworzone",
        "composing_mails": "Tworzenie e-maili",
        "bucket_List": "Lista bucketów",
        "allowed_sending_addresses": "Adresy mogące wysyłać",
        "account_disable_correctly": "Konto zostało wyłączone.",
        "apply_hsm_policy_after_the_restore": "Zastosuj politykę HSM po przywróceniu",
        "data_volumes": "Woluminy",
        "deleting_account_content_3": "Możesz zamiast tego <bold>wyłączyć je, aby zachować dane.</bold>",
        "empty_table": "Tabela jest pusta",
        "global_address_list": "Globalna Lista Adresów",
        "members_only": "Tylko członkowie",
        "owners_manage_add_list": "Właściciele mogą dodawać i usuwać członków, zmieniać wyświetlaną nazwę i opis, zmieniać widoczność listy (np. ukryć ją z GLA), zmieniać właściecieli, modyfikować ustawienia subskrypcji/cofnięcia subskrypcji",
        "server_details": "Szczegóły serwera",
        "this_list_can_receive_email": "Ta lista może otrzymywać e-maile",
        "virtual_host_user_msg_2": "Wirtualne hosty muszą być unikalne dla domeny, aby system mógł zrozumieć który użytkownik należy do której domeny oraz by można było pokazać dopasowane ustawienia dla domeny",
        "volume_deleted": "Wolumin został usunięty",
        "login_is_disabled": "Logowanie jest wyłączone",
        "enable_current_helptext": "Włączenie tej opcji spowoduje wyłączenie aktywnego bieżącego woluminu.",
        "volume_detail_error": "{{message}}",
        "disabled": "Wyłączone",
        "scheduled": "Zaplanowane",
        "backup_at_startup": "Kopia zapasowa przy uruchomieniu",
        "resource_deleted_successfully": "{{resource_name}} zostało usunięte",
        "rt_status": "Status RT",
        "you_are_deleting_ml": "Usuwasz {{name}}",
        "ext_volume": "Wolumin zewnętrzny",
        "OTP": "Hasło OTP",
        "e_mail": "E-mail",
        "global": "Globalne",
        "reset": "Zresetuj",
        "service": "Usługa",
        "update": "Zaktualizuj",
        "background_description": "Wklej URL obrazka ekranu logowania. Uzyj pliku JPG, o rozdzielczości 2560x1440 pikseli, max. 800 KB.",
        "wiping_device_warning_msg_1": "Wyczyszczenie urządzenia cofnie je do ustawień fabrycznych. Czy na pewno chcesz kontynuować?",
        "NEW_OTP": "NOWE HASŁO OTP",
        "admin_panel_title": "PANEL ADMINISTRACYJNY",
        "background_login_page": "Tło ekranu logowania",
        "create_otp": "STWÓRZ HASŁO OTP",
        "admin_panel_theme_description": "W tej sekcji możesz dostosować panel administracyjny logiem i obrazkiem twojej organizacji.",
        "eligible_servers": "Dostępne serwery",
        "failed": "Nie powiodło się",
        "favicon_path": "Ścieżka ikonki w karcie przeglądarki (favicon)",
        "end_user_webapp": "Klient sieciowy dla użytkownika końcowego",
        "logo": "Logo",
        "logo_path": "Ścieżka loga",
        "mountpoint": "Mountpoint",
        "object_storage": "Pamięć obiektów",
        "primary_volume": "To jest wolumin pierwszorzędny",
        "reset_domain_theme": "Zresetuj motyw {{name}}",
        "secondary_volume": "To jest wolumin drugorzędny",
        "selected_empty_bucket": "Nie wybrano żadnego bucketa. Zacznij wpisywać w polu powyżej, aby wyświetlić buckety.",
        "suspend": "Zawieś",
        "use_https_protocol_message": "Musisz użyć protokołu HTTPS",
        "wipe_device_factory_settings": "Cofnij urządzenia do ustawień fabrycznych",
        "you_are_trying_wipe_device": "Próbujesz wyczyścić urządzenie",
        "bucket_delete_button": "USUŃ",
        "open": "Otwórz",
        "verify_certificate": "Zweryfikuj",
        "new_virtual_host_name": "Wpisz nową nazwę wirtualnego hosta i kliknij w \"Dodaj +\", aby dodać ją do listy",
        "certificate_alert_helperText": "Certyfikat stanie się dostępny kiedy proxy zostanie zrestartowane",
        "default_mail_quota_for_account_domain": "Domyślny limit przestrzeni dla skrzynki pocztowej każdego konta w domenie",
        "domain_certificate_ca_chain": "Łańcuch CA certyfikatu domeny",
        "load_FILE": "PRZEŚLIJ PLIK",
        "load_your_cert_file": "Prześlij plik z certyfikatem",
        "private_key_certificate": "Prywatny klucz certyfikatu",
        "virtual_hosts_and_certificates": "Wirtualne hosty i certyfikaty",
        "done": "Gotowe",
        "operation": {
            "get_all_operation_error": "{{name}}"
        },
        "stop_operation_helperText": "{{message}}",
        "restore_config_info_row_1": "Konto <bold>{{accountName}}</bold> zostanie skopiowane na konto, które wybierzesz w polu poniżej.",
        "storage_centralized_helpertext": "<bold>Użyj CLI, aby zarządzać centralizacją.</bold> Zcentralizowane dane mogą okazać się przydatne, gdy dwa lub więcej serwerów potrzebuje dostępu do tych samych danych. Trzymając dane w jednym miejscu, łatwiej jest zarządzać urządzeniami jak i samymi danymi. ",
        "disable_the_account": "Wyłącz konto",
        "prefix_name": "Prefiks - wszystkie obiekty będą miały ten prefiks w swojej nazwie",
        "type_of_volume": "Typ woluminu",
        "volume_as_current": "Wolumin jako bieżący",
        "volume_detail_page_title": "Szczegóły {{message}}",
        "Rights": "Uprawnienia",
        "files": "Pliki",
        "tasks": "Zadania",
        "cos_primarybar_tooltip": "Zobacz i zarządzaj szczegółami oraz funkcjami Twoich <bold>klas usług, pulami serwerów i zaawansowanymi ustawieniami.</bold>",
        "example_lbl": "Przykład:",
        "notification_primarybar_tooltip": "Zobacz swoje <bold>powiadomienia</bold> i oznaczaj je jako przeczytane lub kopiuj, aby je udostępnić.",
        "save_mails_to": "Zapisuj e-maile do",
        "sort_by_total_quota": "Sortuj wg limitu przydziału",
        "storage": "Pamięć",
        "save_a_copy_of_sent_messages_to_delegates_sent_folder": "Zapisuj kopię wysyłanych wiadomości do folderu wysłane pełnomocnika",
        "value": "Wartość",
        "backup_lbl": "<bold>Kopia zapasowa</bold>",
        "change_to": "ZMIEŃ NA",
        "class_of_service_lbl": "<bold>Klasa usługi</bold>",
        "create_account_button": "STWÓRZ KONTO",
        "delete_account": "Czy na pewno chcesz usunąć {{accountId}}?",
        "delete_domain_with_all_resources_pre_msg": "Domena {{domainName}} nie jest pusta i zawiera",
        "dn_settings": "Ustawienia DN",
        "entity_id_copied": "EntityID zostało skopiowane",
        "galsync_account": "Konto GLASync",
        "import_saml_metadata_from_idp": "Importuj metadane SAML od dostawcy tożsamości",
        "ldap_url": "URL LDAP",
        "prefix_volume": "Prefiks - {{volumePrefix}}",
        "saml": "SAML",
        "select_an_attribute_to_show_its_value": "Wybierz atrybut, aby wyświetlić jego wartość",
        "storage_lbl": "<bold>Pamięć</bold>",
        "user_ssl": "Używaj SSL",
        "you_have_exported_the_configuration": "Wyeksportowałeś konfigurację",
        "delete_domain_with_all_resources_msg": "Domena {{domainName}} nie jest pusta i zawiera {{domainRegularAccounts}} kont, {{domainSystemAccounts}} kont systemowych, {{distributionList}} list dystrybucyjnych, {{aliases}} aliasów i {{resources}} zasobów. Jeżeli nie jesteś pewien czy chcesz ją usunąć, możesz ją zamknąć. W ten sposób unikniesz kolejnych interakcji z nią a wszystkie zasoby pozostaną dostępne w razie potrzeby. Możesz też trwale usunąć wszystkie konta i obiekty domeny. Tej operacji nie da się cofnąć.",
        "measure_unit": "Jednostka miary",
        "notification_lbl": "<bold>Powiadomienia</bold>",
        "primary_color_hint": "Aby zmienić główny kolor, użyj kodu koloru w formacie HEX."
    },
    "backup": {
        "backup_purge": "Wyczyszczenie kopii zapasowej",
        "ldap_dump": "LDAP Dump",
        "purge_old_configurations": "Wyczyść stare konfiguracje",
        "threads_for_account": "Wątki dla konta",
        "max_waiting_time": "Max. czas oczekiwania",
        "enable_realtime_scanner": "Włącz Realtime Scanner",
        "schedule_smart_scan": "Zaplanuj SmartScan",
        "force_backup_purge_now": "Wymuś wyczyszczenie kopii zapasowej teraz",
        "max_waiting_time_ms": "Max. czas oczekiwania (ms)",
        "schedule_smartscan": "Zaplanuj SmartScan",
        "latency_high_threshold_ms": "Max. próg opóźnienia (ms)",
        "back_delete_account_warning_message": "Jeśli ustawisz 0, <strong>konta</strong> będą przechowywane w kopii zapasowej na zawsze",
        "force_start_smartscan_now": "Wymuś rozpoczęcie SmartScan teraz",
        "local_volume": "Lokalny wolumin",
        "on_the_fly_metadata": "Metadane w czasie rzeczywistym",
        "schedule_automatic_retention_policies": "Ustaw stałą politykę przechowywania",
        "start_service": "Uruchom usługę",
        "the_service_is": "Usługa",
        "bucket_list": "Lista Bucketów",
        "local_mountpoint": "Lokalny mountpoint"
    },
    "cos": {
        "calendar_options": "Ustawienia kalendarza",
        "display_external_images_in_HTML_mail": "Wyświetla zewnętrzne obrazy w wiadomościach w formacie HTML",
        "enable_toaster_notification_for_new_mail": "Włącz powiadomienia pop-up dla nowych wiadomości",
        "general_information": "Informacje ogólne",
        "language": "Język",
        "number_of_items_to_display_per_page": "Liczba elementów wyświetlanych na stronie",
        "receiving_mail": "Otrzymywanie e-maili",
        "view_mail_as_html": "Wyświetlaj e-maile jako HTML (kiedy to możliwe)",
        "show_search_string": "Pokazuj search string",
        "main_features": "Główne funkcje",
        "spam_message_lifetime": "Okres dostępności wiadomości oznaczonej jako spam",
        "time_window_failed_logins_must_occur_to_lock_account": "Okres kolejnych nieudanych logowań prowadzących do blokady",
        "account_quota": "Limit przestrzeni konta",
        "as_new_mail_arrives": "Po odebraniu nowego e-maila",
        "calendar_polling_interval": "Interwał sprawdzania kalendarza",
        "default_view": {
            "list": "Widok listy"
        },
        "disable_attachment_viewing_from_web_mail_ui": "Wyłącz podgląd załączników w interfejsie www systemu pocztowego",
        "enable_failed_login_lockout": "Włącz blokowanie konta po nieudanym zalogowaniu",
        "free_busy_interop": "Współdziałanie z Wolny/zajęty",
        "manuallly": "Ręcznie",
        "maximum_password_length": "Max. długość hasła",
        "minimum_number_of_unique_password_history": "Min. liczba historii unikalnych haseł",
        "minimum_password_length": "Min. długość hasła",
        "offline_support_for_advanced_client": "Wsparcie offline dla zaawansowanego klienta Ajax",
        "proxy_allowed_domain_name": "Nazwy domen dopuszczonych przez proxy",
        "rss_polling_interval": "Interwał sprawdzania kanału RSS",
        "new_proxy_allowed_domain": "Nowa domena dopuszczona przez Proxy",
        "use_gal_to_auto_fill": "Używaj GLA do automatycznego uzupełniania",
        "search_a_specific_server": "Wyszukaj konkretny serwer",
        "out_of_the_office_reply": "Odpowiedź Poza biurem",
        "limt_serverpool_avaiable_create_user": "Ogranicz pulę serwerów dostępną do tworzenia nowych użytkowników w tym COS",
        "external_pop_access": "Zewnętrzny dostęp POP",
        "enable_auto_add_contacts": "Włącz automatyczne dodawanie kontaktów",
        "default_charset": "Domyślny zestaw znaków",
        "auto_decline_if_inviter_is_blacklisted": "Automatycznie odrzucaj jeśli nadawca znajduje się na czarnej liście",
        "add_invites_with_publish_method": "Dodawaj zaproszenia metodą PUBLISH",
        "active_sync": "ActiveSync",
        "files": "Pliki"
    },
    "locale": {
        "label_portuguese": "Portugalski - {{value}}",
        "label_spanish": "Hiszpański - {{value}}",
        "portuguese_brazil": "Portugalski (Brazylia)",
        "thai": "Tajski",
        "dutch": "Niderlandzki",
        "italian": "Włoski",
        "label_english": "Angielski - {{value}}",
        "vietnamese": "Wietnamski"
    },
    "accountDetails": {
        "user_will_change_password_on_next_login": "Użytkownik musi zmienić hasło przy następnym logowaniu"
    },
    "select_domain_or_create_new": "Wybierz domenę z menu po lewej stronie lub kliknij przycisk \"Stwórz\", aby stworzyć nową.",
    "new_bucket_connection": "POŁĄCZENIE",
    "create_new_domain": "Stwórz nową domenę",
    "commons": {
        "confirm_connection": "POTWIERDŹ POŁĄCZENIE"
    },
    "account_details": {
        "add_invites_with_publish_method": "Dodawaj zaproszenia metodą PUBLISH",
        "as_new_mail_arrives": "Po odebraniu nowego e-maila",
        "default_COS": "Domyślne COS",
        "default_view": {
            "week": "Widok tygodnia"
        },
        "hide_in_gal": "Ukryj w GLA",
        "offline_support_for_advanced_ajax_client": "Wsparcie offline dla zaawansowanego klienta Ajax",
        "send_read_receipts": "Wysyłaj potwierdzenia przeczytania",
        "enable_toast_for_new_emails": "Włącz powiadomienia dla nowych e-maili",
        "use_quickadd_dialog_in_creation": "Używaj dialogu QuickAdd podczas tworzenia",
        "this_is_global_administrator": "To jest administrator globalny ",
        "show_time_zone_lists_in_view": "Pokazuj listę stref czasowych w widoku spotkań",
        "out_of_office_reply": "Odpowiedź Poza biurem",
        "mail_signatures": "Podpisy e-mail",
        "html_compose": "Tworzenie HTML",
        "forwarding_addresses_specified_by_the_user": "Adresy przekazywania dalej określone przez użytkownika",
        "enable_auto_add_contacts": "Włącz automatyczne dodawanie kontaktów",
        "display_external_image_as_html": "Wyświetlaj zewnętrzne obrazy jako HTML",
        "browser_title_for_appointments": "Podświetl tytuł strony w przeglądarce dla spotkań",
        "appointments_default_duration": "Domyślna długość trwania spotkania",
        "please_note_code": "Uwaga: będzie można zobaczyć te kody tylko raz.",
        "activesync_remote_access": "Zdalny dostęp ActiveSync",
        "type_the_new_alias_name": "Wpisz nową nazwę aliasu i wybierz domenę, aby dodać go do dostępnych aliasów",
        "manage_the_aliases_for_this_account": "Zarządzaj aliasami dla tego konta",
        "NEXT": "DALEJ",
        "send_as_behalf": "Wysyłanie w imieniu (odbiorcy będą widzieć {{targetEmail}} jako adres nadawcy)",
        "ADD": "DODAJ",
        "as": "jako",
        "i_want_to_create_a_delegate_for": "Chcę stworzyć pełnomocnika dla",
        "select_delegate_folder": "Wybierz, które foldery pełnomocnik może wyświetlać",
        "send_read_manage_mails": "Wysyłanie, wyświetlanie i zarządzanie e-mailami (wszystko z powyższych)",
        "set_rights": "NADAJ UPRAWNIENIA",
        "what_rights_will_the_delegate_have": "Jakie uprawnienia będzie miał pełnomocnik?",
        "DELETE": "USUŃ",
        "remove": "Usuń",
        "able_to_see_password_once": " Uwaga: będziesz w stanie zobaczyć hasło <bold>tylko raz.</bold>",
        "account_with_read_write_rights": "Konta z uprawnieniami <bold>wyświetlanie/wysyłanie</bold>",
        "manage_no_rights_to_send_mails": "Zarządzanie (brak uprawnień do wysyłania e-maili)",
        "remove_all": "USUŃ WSZYSTKO",
        "switch_simplified": "Przełącz na uproszczony widok",
        "passphrasaId": "ID hasła"
    },
    "privacy": {
        "survey_feedback_sub_1": "Nie martw się, ankiety będą szybkie, proste i bardzo pomogą nam zrozumieć co robimy dobrze a co źle.",
        "allow_data_analytics": "Zezwalaj na analitykę danych"
    },
    "connection": {
        "arn_name": "Arn / Nazwa"
    },
    "volume": {
        "serverName_volumes_create_mailstores_volume": "Stwórz wolumin magazynu poczty w {{serverName}}",
        "server_list_header": {
            "index": "Indeks",
            "indexer": "Indeksowanie"
        },
        "volume_allocation_list": {
            "external": "Zewnętrzne",
            "object_storage": "Pamięć obiektów"
        },
        "volume_config_header": {
            "status": "Status"
        },
        "volume_header": {
            "name": "Nazwa"
        },
        "volume_indexer_header": {
            "id": "ID"
        },
        "volume_type": {
            "primary": "Pierwszorzędny"
        },
        "indexer_helperText": "Indeksowanie"
    },
    "hsm": {
        "all": "Wszystkie",
        "create_policy": "Stwórz politykę",
        "delete": "Usuń",
        "edit": "Edytuj",
        "hsm_policies_list": "Lista polityk HSM",
        "kb": "KB",
        "minutes": "Minuty",
        "no": "Nie",
        "primary": "Pierwszorzędny",
        "server": "Serwer",
        "value": "Wartość",
        "abstract_msg_1": "<strong>{{enables}}{{largerSmaller}}</strong>. To wpłynie na dane przechowywane w <bold>{{previous}}</bold> i w <bold>{{next}}</bold>.",
        "all_secondary_volume_used_source_msg": "Aktualny wolumin drugorzędny zostanie użyty jako docelowy. Możesz też ręcznie wybrać inne woluminy.",
        "create_new_policy": "Stwórz nową politykę",
        "hsm_policy_correctly_deleted": "Polityka HSM została usunięta",
        "new_policy": "Nowa polityka",
        "policy_name": "Nazwa polityki",
        "smaller_size_than": "mniejsze niż <bold>{{measure}} {{scale}}</bold>",
        "scheduling": "Harmonogram"
    },
    "welcome_to_carbonio_display_name": "Witaj, {{adminName}}!",
    "dashboard": {
        "carbonio_core": "Carbonio Rdzeń",
        "quick_access_to": "Szybki dostęp do",
        "core_version": "Wersja rdzenia"
    },
    "notification": {
        "mark_as_read": "Oznacz jako przeczytane",
        "error": "BŁĄD",
        "notification_mark_unread_successfully": "Powiadomienie zostało oznaczone jako nieprzeczytane"
    },
    "to_carbonio": "do Carbonio!",
    "virtual_hosts": {
        "load_certificate": "PRZEŚLIJ CERTYFIKAT"
    },
    "operations": {
        "copy_operation_successfully": "Powiadomienie zostało skopiowane",
        "label": {
            "notifications": "Notifications",
            "create_fake_blob": "Stwórz fake blob",
            "read_error_threshold": "Próg wyświetlania błędu",
            "stop_operation_btn": "ZATRZYMAJ OPERACJĘ"
        },
        "operations_list_header": {
            "server": "Serwer"
        },
        "other": "Inne",
        "cancel_operation_model_title": "Anulujesz operację {{OperationName}}",
        "queued_panel_heading": "Operacje w kolejce",
        "stopping_operation_model_title_helperText": "Zatrzymujesz operację {{operationName}}"
    },
    "modal": {
        "iscurrent_confirm": {
            "title": "Ustawiasz {{name}} jako aktualny"
        }
    },
    "warning": {
        "is_current": "Musisz najpierw ustawić inny wolumin jako aktualny."
    },
    "unsupported_version": "Serwer wysłał nieprawidłową odpowiedź. Skontaktuj się z administratorem serwera",
    "all_rights_reserved": "Wszelkie prawa zastrzeżone",
    "auth_not_valid": "Polityka uwierzytelniania wymaga dalszych kroków: skontaktuj się z administratorem, aby uzyskać więcej informacji",
    "changePassword_error_minLength": "Min. długość to {{num}} znaków",
    "changePassword_error_minPunctuationChars": "Wymagane min. {{num}} znaków interpunkcyjnych",
    "offline": "Jesteś offline, sprawdź swoje połączenie internetowe",
    "cant_login": "Nie da się obecnie zalogować",
    "carbonio_authentication": "Carbonio Uwierzytelnianie",
    "changePassword_confirmNewPassword": "Potwierdź nowe hasło",
    "changePassword_confirm_label": "Zmień hasło a następnie się zaloguj",
    "changePassword_error_confirmPassword": "Hasła nie są identyczne",
    "changePassword_error_maxLength": "Max. długość to {{num}} znaków",
    "server_not_responding": "Serwer nie odpowiada. Skontaktuj się z administratorem serwera",
    "supported_browsers": "Wspierane przeglądarki",
    "trust_device_and_ip": "Ufaj temu urzędzeniu i adresowi IP",
    "two_step_authentication": "Uwierzytelnianie dwuetapowe",
    "type_otp": "Wpisz tutaj hasło OTP",
    "username": "Nazwa użytkownika",
    "wrong_password": "Błędne hasło, sprawdź dane i spróbuj ponownie",
    "changePassword_error_minLowerCaseChars": "Wymagane min. {{num}} małych liter",
    "changePassword_error_minNumericChars": "Wymagane min. {{num}} cyfr",
    "changePassword_error_minUppercaseChars": "Wymagane min. {{num}} wielkich liter",
    "changePassword_error_passwordRecentlyUsed": "Hasło było niedawno używane",
    "changePassword_newPassword": "Nowe hasło",
    "changePassword_oldPassword": "Stare hasło",
    "changePassword_title": "Stwórz nowe hasło",
    "choose_otp": "Wybierz metodę hasła OTP",
    "copy_right": "Prawa autorskie",
    "credentials_not_valid": "Dane logowania są nieprawidłowe, sprawdź dane i spróbuj ponownie",
    "details": "Szczegóły",
    "login": "Zaloguj się",
    "login_saml": "Zaloguj się SAML",
    "password": "Hasło"
}
